flake8_override/__init__.py
flake8_override/plugin.py
flake8_override/py.typed
flake8_override-0.1.0.dist-info/METADATA
flake8_override-0.1.0.dist-info/WHEEL
flake8_override-0.1.0.dist-info/entry_points.txt
flake8_override-0.1.0.dist-info/licenses/LICENSE
flake8_override-0.1.0.dist-info/RECORD
